{
  "id": "phase5-polish-qa",
  "name": "phase5-polish-qa",
  "title": "阶段5：桌面适配、性能与验收",
  "description": "Windows 适配、性能优化、空状态、验收与回归",
  "status": "completed",
  "dev_type": null,
  "scope": null,
  "package": null,
  "priority": "P2",
  "creator": "lingshichat",
  "assignee": "lingshichat",
  "createdAt": "2026-04-19",
  "completedAt": "2026-04-25",
  "branch": null,
  "base_branch": "main",
  "worktree_path": null,
  "current_phase": 0,
  "next_action": [
    {
      "phase": 1,
      "action": "brainstorm"
    },
    {
      "phase": 2,
      "action": "research"
    },
    {
      "phase": 3,
      "action": "implement"
    },
    {
      "phase": 4,
      "action": "check"
    },
    {
      "phase": 5,
      "action": "update-spec"
    },
    {
      "phase": 6,
      "action": "record-session"
    }
  ],
  "commit": null,
  "pr_url": null,
  "subtasks": [],
  "children": [],
  "parent": "04-18-flutter-media-tracker",
  "relatedFiles": [],
  "notes": "",
  "meta": {}
}